poplar_oeaddlne/OE0500_oe_add_line.py
poplar_oeaddlne/OE1100_oe_add_line.py
poplar_oeaddlne/__init__.py
poplar_oeaddlne/resources/__init__.py
poplar_oeaddlne/resources/all_view_calls.py
poplar_oeaddlne/resources/examples/OE1100.AddFieldToScreen.py
poplar_oeaddlne/resources/examples/OE1100.AddFreightButton.py
poplar_oeaddlne/resources/examples/OE1100.ChangeCustomerFinder.py
poplar_oeaddlne/resources/examples/OE1100.ChangeGridFinder.py
poplar_oeaddlne/resources/examples/OE1100.ChangeShipviaFinder.py
poplar_oeaddlne/resources/examples/OE1100.HideField.py
poplar_oeaddlne/resources/examples/__init__.py
poplar_oeaddlne/vi/OEADDLNE.vi
poplar_oeaddlne-1.1.0.dist-info/LICENSE.txt
poplar_oeaddlne-1.1.0.dist-info/METADATA
poplar_oeaddlne-1.1.0.dist-info/WHEEL
poplar_oeaddlne-1.1.0.dist-info/top_level.txt
poplar_oeaddlne-1.1.0.dist-info/RECORD
